overkiz_exporter.py
overkiz_exporter-1.2.0.dist-info/METADATA
overkiz_exporter-1.2.0.dist-info/WHEEL
overkiz_exporter-1.2.0.dist-info/RECORD
