Metadata-Version: 2.3
Name: overkiz-exporter
Version: 1.2.0
Summary: 
Author: François Schmidts
Author-email: francois@schmidts.fr
Requires-Python: >=3.13,<4.0
Classifier: Development Status :: 5 - Production/Stable
Classifier: Topic :: Home Automation
Classifier: Topic :: System :: Monitoring
Requires-Dist: daemon-metrics (>=1.0.0,<2.0.0)
Requires-Dist: prometheus-client (>=0.21.1)
Requires-Dist: pyoverkiz (>=1.15.3)
Requires-Dist: the-conf (>=1.0.1)
